tokn/__init__.py
tokn-0.0.0.dist-info/METADATA
tokn-0.0.0.dist-info/WHEEL
tokn-0.0.0.dist-info/top_level.txt
tokn-0.0.0.dist-info/RECORD
