Metadata-Version: 2.1
Name: tokn
Version: 0.0.0
Summary: Working on some new ideas for LLM tokenization. WIP, coming soon...
Author-email: Ola Næss Kaldestad <mail@okal.no>
